[
    {
        "readingId": 21185497,
        "title": "",
        "content": "",
        "answer": "",
        "lessonId": 21178181,
        "order": 1,
        "partId": 0,
        "isAudio": false,
        "audioUrl": "",
        "score": 0,
        "questionScore": 10,
        "listQuestion": [
            {
                "questionId": 21185503,
                "lessonId": 0,
                "a": "Tứ giác lồi là tứ giác mà hai đỉnh thuộc một cạnh bất kì luôn nằm về một phía của đường \tthẳng đi qua hai đỉnh còn lại.",
                "b": "Tổng các góc của một tứ giác bằng <img style = \"vertical-align:middle\" src= \"https://asset.moon.vn/new-latex/2025/10/235e7f9c-fd26-4375-888c-0ab818d7a576.png\"/>",
                "c": "Tổng các góc của một tứ giác bằng <img style = \"vertical-align:middle\" src= \"https://asset.moon.vn/new-latex/2025/10/c068ca45-10be-42fd-91dc-0366b0b8068e.png\"/>",
                "d": "Tứ giác <img style = \"vertical-align:middle\" src= \"https://asset.moon.vn/new-latex/2025/10/7abe44d4-aa75-45b0-bbea-c5b89278f446.png\"/> là hình gồm đoạn thẳng <img style = \"vertical-align:middle\" src= \"https://asset.moon.vn/new-latex/2025/10/1d9ba338-d4ce-4358-b542-45e622c38faf.png\"/> trong đó bất kì hai đoạn thẳng nào cũng không nằm trên một đường thẳng.",
                "bookId": 1055470,
                "comments": 2,
                "bookmarks": 0,
                "likes": 0,
                "shares": 0,
                "typeId": 0,
                "questionText": "Trong các khẳng định sau, khẳng định nào <b>không</b> đúng?",
                "answer": "<b>🔍 Phương pháp</b><br>Ta sẽ phân tích từng khẳng định để xác định tính đúng sai của chúng dựa trên các định lý và định nghĩa cơ bản về hình tứ giác.<br><br><b>✍️ Lời giải chi tiết</b><br><b>A.</b> <i>Tứ giác lồi là tứ giác mà hai đỉnh thuộc một cạnh bất kì luôn nằm về một phía của đường thẳng đi qua hai đỉnh còn lại.</i><br>Khẳng định này <b>không đúng</b>. Định nghĩa chính xác của tứ giác lồi là: \"Tứ giác lồi là tứ giác luôn nằm trong một nửa mặt phẳng có bờ là đường thẳng chứa bất kì cạnh nào của tứ giác đó\".<br><br><b>B.</b> <i>Tổng các góc của một tứ giác bằng <img style = \"vertical-align:middle\" src= \"https://asset.moon.vn/new-latex/2025/10/44607f0e-c7ae-4886-9c21-000b671e473b.png\"/>.</i><br>Khẳng định này <b>không đúng</b>. Tổng các góc của một <b>tam giác</b> bằng <img style = \"vertical-align:middle\" src= \"https://asset.moon.vn/new-latex/2025/10/1dae41ac-0e9e-44b0-bed0-d171d2af2ff6.png\"/>.<br><br><b>C.</b> <i>Tổng các góc của một tứ giác bằng <img style = \"vertical-align:middle\" src= \"https://asset.moon.vn/new-latex/2025/10/cd2a0ece-43c4-4e28-9002-d6c4372ea779.png\"/>.</i><br>Khẳng định này <b>đúng</b>. Đây là một định lý cơ bản trong hình học.<br><br><b>D.</b> <i>Tứ giác ABCD là hình gồm đoạn thẳng AB, BC, CD, DA, trong đó bất kì hai đoạn thẳng nào cũng không nằm trên một đường thẳng.</i><br>Khẳng định này <b>đúng</b>. Đây là một cách định nghĩa hình tứ giác đơn (không tự cắt).<br><br><b>So sánh các khẳng định không đúng:</b><br>Cả A và B đều là các khẳng định sai. Tuy nhiên, khẳng định B là một sai lầm kiến thức cơ bản và trực tiếp mâu thuẫn với khẳng định đúng C. Trong các câu hỏi trắc nghiệm, đây thường là đáp án sai cần tìm.<br><br><b>✅ Kết luận: Chọn đáp án B</b><br>",
                "key": "B",
                "isVideo": true,
                "score": 0,
                "order": 1,
                "fillKey": "",
                "yourKey": "",
                "isTested": false,
                "isBookmark": false,
                "liked": false,
                "questionScore": 0.5,
                "plans": [],
                "answerPlans": []
            },
            {
                "questionId": 21185505,
                "lessonId": 0,
                "a": "Tứ giác có 4 đường chéo.",
                "b": "Tổng các góc của một tứ giác bằng <img style = \"vertical-align:middle\" src= \"https://asset.moon.vn/new-latex/2025/10/22e639ab-887a-4887-aa30-323fb684b229.png\"/>",
                "c": "Tồn tại một tứ giác có 1 góc tù và 3 góc vuông.",
                "d": "Tứ giác lồi là tứ giác luôn nằm về một phía của đường thẳng chứa một cạnh bất kì của tứ \tgiác đó.",
                "bookId": 1055471,
                "comments": 0,
                "bookmarks": 1,
                "likes": 0,
                "shares": 0,
                "typeId": 0,
                "questionText": "Khẳng định nào sau đây là đúng?",
                "answer": "<b>🔍 Phương pháp</b><br>Ta sẽ phân tích tính đúng/sai của từng khẳng định dựa trên các định nghĩa và định lý cơ bản về hình tứ giác.<br><b>✍️ Lời giải chi tiết</b><br><b>A.</b> <i>Tứ giác có 4 đường chéo.</i><br>Khẳng định này <b>sai</b>. Một tứ giác có 4 đỉnh, do đó chỉ có 2 đường chéo (đoạn thẳng nối hai đỉnh không kề nhau).<br><b>B.</b> <i>Tổng các góc của một tứ giác bằng <img style = \"vertical-align:middle\" src= \"https://asset.moon.vn/new-latex/2025/10/2207802c-b5f9-4b77-9526-afe6968057d8.png\"/>.</i><br>Khẳng định này <b>sai</b>. Tổng các góc của một <b>tam giác</b> là <img style = \"vertical-align:middle\" src= \"https://asset.moon.vn/new-latex/2025/10/3c42fb00-84e5-47ca-8832-02c61da94cb4.png\"/>. Tổng các góc của một tứ giác luôn bằng <img style = \"vertical-align:middle\" src= \"https://asset.moon.vn/new-latex/2025/10/ae380cc4-26cf-47bb-a3c3-af768f638c88.png\"/>.<br><b>C.</b> <i>Tồn tại một tứ giác có 1 góc tù và 3 góc vuông.</i><br>Khẳng định này <b>sai</b>. Ba góc vuông có tổng là <img style = \"vertical-align:middle\" src= \"https://asset.moon.vn/new-latex/2025/10/c07c889c-4f3d-45bd-bc4c-0be3435acd41.png\"/>. Vì tổng các góc của tứ giác là <img style = \"vertical-align:middle\" src= \"https://asset.moon.vn/new-latex/2025/10/f2b87c5c-806e-4e93-80f2-43d3c20b86d6.png\"/>, góc còn lại phải là <img style = \"vertical-align:middle\" src= \"https://asset.moon.vn/new-latex/2025/10/9656e58a-b9e8-4e2b-9b2f-acd4ad8fa454.png\"/>, tức là một góc vuông, không thể là góc tù.<br><b>D.</b> <i>Tứ giác lồi là tứ giác luôn nằm về một phía của đường thẳng chứa một cạnh bất kì của tứ giác đó.</i><br>Khẳng định này <b>đúng</b>. Đây là định nghĩa chính xác của một tứ giác lồi.<br><b>✅ Kết luận: Chọn đáp án D</b><br>",
                "key": "D",
                "isVideo": true,
                "score": 0,
                "order": 2,
                "fillKey": "",
                "yourKey": "",
                "isTested": false,
                "isBookmark": false,
                "liked": false,
                "questionScore": 0.5,
                "plans": [],
                "answerPlans": []
            },
            {
                "questionId": 21185508,
                "lessonId": 0,
                "a": "4 góc nhọn.",
                "b": "4 góc tù.",
                "c": "4 góc vuông.",
                "d": "1 góc vuông, 3 góc nhọn.",
                "bookId": 1055472,
                "comments": 0,
                "bookmarks": 2,
                "likes": 0,
                "shares": 0,
                "typeId": 0,
                "questionText": "Các góc của một tứ giác có thể là",
                "answer": "<b>🔍 Phương pháp</b><br>Ta sử dụng định lý rằng tổng số đo bốn góc trong một tứ giác lồi luôn bằng <img style = \"vertical-align:middle\" src= \"https://asset.moon.vn/new-latex/2025/10/a9388b94-101f-477c-be88-e1e2c5907c18.png\"/>. Sau đó, ta sẽ xét tổng số đo các góc trong từng trường hợp để xác định khẳng định nào có thể xảy ra.<br><b>✍️ Lời giải chi tiết</b><br>Ta có tổng các góc của một tứ giác là <img style = \"vertical-align:middle\" src= \"https://asset.moon.vn/new-latex/2025/10/3aee185d-5431-4e7a-8e7e-45c425eb1e96.png\"/>.<br><b>A.</b> <i>4 góc nhọn.</i><br>Một góc nhọn có số đo nhỏ hơn <img style = \"vertical-align:middle\" src= \"https://asset.moon.vn/new-latex/2025/10/9f6a95be-76bb-4642-98ff-40fba1190b8d.png\"/>. Do đó, tổng của 4 góc nhọn sẽ nhỏ hơn <img style = \"vertical-align:middle\" src= \"https://asset.moon.vn/new-latex/2025/10/7948d73f-4d24-445e-a69e-7605828c9aab.png\"/>. Vì vậy, trường hợp này không thể xảy ra.<br><b>B.</b> <i>4 góc tù.</i><br>Một góc tù có số đo lớn hơn <img style = \"vertical-align:middle\" src= \"https://asset.moon.vn/new-latex/2025/10/1cc97713-c71d-487b-b6d5-658e7e4a9bbc.png\"/>. Do đó, tổng của 4 góc tù sẽ lớn hơn <img style = \"vertical-align:middle\" src= \"https://asset.moon.vn/new-latex/2025/10/c6af9ff2-96d9-4ebb-93a7-c6fc822d5f3c.png\"/>. Vì vậy, trường hợp này cũng không thể xảy ra.<br><b>C.</b> <i>4 góc vuông.</i><br>Một góc vuông có số đo bằng <img style = \"vertical-align:middle\" src= \"https://asset.moon.vn/new-latex/2025/10/85dc1b01-7796-4a47-8df1-20ab81716d9e.png\"/>. Tổng của 4 góc vuông là <img style = \"vertical-align:middle\" src= \"https://asset.moon.vn/new-latex/2025/10/89cee98f-7875-408d-ac56-653cfe79c3a0.png\"/>. Điều này hoàn toàn có thể xảy ra, ví dụ như trong hình chữ nhật hoặc hình vuông.<br><b>D.</b> <i>1 góc vuông, 3 góc nhọn.</i><br>Tổng của 1 góc vuông và 3 góc nhọn sẽ là <img style = \"vertical-align:middle\" src= \"https://asset.moon.vn/new-latex/2025/10/3a153293-59f3-41cb-a6f2-1f6f107e33c8.png\"/> + (tổng 3 góc nhọn). Vì tổng 3 góc nhọn nhỏ hơn <img style = \"vertical-align:middle\" src= \"https://asset.moon.vn/new-latex/2025/10/d20979ce-de51-40ef-9784-fcd206b18a41.png\"/>, nên tổng cả 4 góc sẽ nhỏ hơn <img style = \"vertical-align:middle\" src= \"https://asset.moon.vn/new-latex/2025/10/626b908e-e8dc-4c87-98cd-2423ad2dddfd.png\"/>. Vì vậy, trường hợp này không thể xảy ra.<br><b>✅ Kết luận: Chọn đáp án C</b><br>",
                "key": "C",
                "isVideo": true,
                "score": 0,
                "order": 3,
                "fillKey": "",
                "yourKey": "",
                "isTested": false,
                "isBookmark": false,
                "liked": false,
                "questionScore": 0.5,
                "plans": [],
                "answerPlans": []
            },
            {
                "questionId": 21185515,
                "lessonId": 0,
                "a": "BH và HN.",
                "b": "BK và HN.",
                "c": "BN và HK.",
                "d": "HN và NK.",
                "bookId": 1055473,
                "comments": 0,
                "bookmarks": 0,
                "likes": 0,
                "shares": 0,
                "typeId": 0,
                "questionText": "Tứ giác BHNK có hai cạnh đối nhau là",
                "answer": "<img src=\"https://asset.moon.vn/img/chat/large/2025/10/1cb75d1c-b4e9-4f16-822d-28dcab9e9fec.jpg\" data-filename=\"\" style=\"max-width: 600px; height: auto;\"><b><br></b><b>🔍 Phương pháp</b><br>Để xác định các cặp cạnh đối nhau của một tứ giác, ta cần dựa vào tên gọi của tứ giác đó. Tứ giác <b>BHNK</b> có các đỉnh được liệt kê theo thứ tự liên tiếp là B, H, N, K.<br>Các cạnh của tứ giác là: BH, HN, NK, KB.<br>Hai cạnh <b>đối nhau</b> là hai cạnh không có đỉnh chung.<br>Hai cạnh <b>kề nhau</b> là hai cạnh có chung một đỉnh.<br><b>✍️ Lời giải chi tiết</b><br>Dựa vào tên gọi tứ giác <b>BHNK</b>, ta có:<br>Cạnh <b>BH</b> kề với cạnh KB (chung đỉnh B) và cạnh HN (chung đỉnh H). Cạnh không có đỉnh chung với BH là <b>NK</b>. Vậy, <b>BH và NK</b> là một cặp cạnh đối nhau.<br>Cạnh <b>HN</b> kề với cạnh BH (chung đỉnh H) và cạnh NK (chung đỉnh N). Cạnh không có đỉnh chung với HN là <b>KB</b>. Vậy, <b>HN và BK</b> là cặp cạnh đối nhau còn lại.<br>Bây giờ, ta xem xét các lựa chọn:<br><b>A.</b> <b>BH và HN:</b> Hai cạnh này có chung đỉnh H nên là hai cạnh kề nhau.<br><b>B.</b> <b>BK và HN:</b> Hai cạnh này không có đỉnh chung nên là hai cạnh đối nhau.<br><b>C.</b> <b>BN và HK:</b> Đây là hai đường chéo (nối hai đỉnh đối nhau), không phải là cạnh.<br><b>D.</b> <b>HN và NK:</b> Hai cạnh này có chung đỉnh N nên là hai cạnh kề nhau.<br><b>✅ Kết luận: Chọn đáp án B</b><br>",
                "key": " ",
                "isVideo": true,
                "score": 0,
                "order": 4,
                "fillKey": "",
                "yourKey": "",
                "isTested": false,
                "isBookmark": false,
                "liked": false,
                "questionScore": 0.5,
                "plans": [],
                "answerPlans": []
            },
            {
                "questionId": 21185520,
                "lessonId": 0,
                "a": "Hai đỉnh kề nhau là <img style = \"vertical-align:middle\" src= \"https://asset.moon.vn/new-latex/2025/10/c8aeec05-9323-44c1-a15e-e816fb447e06.png\"/> và <img style = \"vertical-align:middle\" src= \"https://asset.moon.vn/new-latex/2025/10/5ee73dce-d165-4591-a39a-562c01857598.png\"/> và <img style = \"vertical-align:middle\" src= \"https://asset.moon.vn/new-latex/2025/10/0319ebca-9ae1-470e-b10d-ed5c0217bae9.png\"/>",
                "b": "Hai đỉnh đối nhau là <img style = \"vertical-align:middle\" src= \"https://asset.moon.vn/new-latex/2025/10/f77b0aba-7877-4f94-9138-eaa9fe8018a7.png\"/> và <img style = \"vertical-align:middle\" src= \"https://asset.moon.vn/new-latex/2025/10/47168ece-3f9c-4b79-8754-1f0dda6338d1.png\"/> và <img style = \"vertical-align:middle\" src= \"https://asset.moon.vn/new-latex/2025/10/837a4cca-0ff1-4f7f-bb96-f65ae299fa9e.png\"/>",
                "c": "Hai đường chéo là <img style = \"vertical-align:middle\" src= \"https://asset.moon.vn/new-latex/2025/10/bca3cb21-358b-4788-8492-53ad9f8bb32f.png\"/>",
                "d": "Các điểm nằm trong tứ giác <img style = \"vertical-align:middle\" src= \"https://asset.moon.vn/new-latex/2025/10/e55529b0-8299-4ed3-a47b-f8960c58e1c6.png\"/> là <img style = \"vertical-align:middle\" src= \"https://asset.moon.vn/new-latex/2025/10/4e87349e-f515-41d4-844b-a8d306d1e1cc.png\"/> và <img style = \"vertical-align:middle\" src= \"https://asset.moon.vn/new-latex/2025/10/5c65769b-5bde-4011-913a-e234980f28b0.png\"/>",
                "bookId": 1055474,
                "comments": 0,
                "bookmarks": 0,
                "likes": 0,
                "shares": 0,
                "typeId": 0,
                "questionText": "Cho hình vẽ dưới đây. Trong các khẳng định sau, khẳng định nào <b>sai</b>?<br><img src=\"https://asset.moon.vn/img/chat/large/2025/10/c40070dd-90e6-4e61-a950-39f5720a66f5.jpg\" data-filename=\"\" style=\"max-width: 600px; height: auto;\">",
                "answer": "<b>🔍 Phương pháp</b><br>Ta sẽ phân tích từng khẳng định dựa trên hình vẽ và các định nghĩa về các yếu tố của một tứ giác (đỉnh kề, đỉnh đối, đường chéo, điểm trong). Khẳng định <b>sai</b> là khẳng định không mô tả đúng các yếu tố này.<br><b>✍️ Lời giải chi tiết</b><br>Xét tứ giác ABCD trong hình vẽ:<br><b>A.</b> Hai đỉnh kề nhau là A và B; A và D.<br>Khẳng định này đúng. Nhìn hình ta thấy được đỉnh A và B kề nhau, A và D kề nhau <br><b>B.</b> Hai đỉnh đối nhau là A và C; B và D.<br>Khẳng định này <b>đúng</b>. Đỉnh A không kề với C (A và C là hai đỉnh đối nhau). Đỉnh B không kề với D (B và D là hai đỉnh đối nhau). Đây là liệt kê đầy đủ 2 cặp đỉnh đối nhau.<br><b>C.</b> Hai đường chéo là AC, BD.<br>Khẳng định này <b>đúng</b>. Đường chéo là đoạn thẳng nối hai đỉnh đối nhau. Tứ giác ABCD có 2 đường chéo là AC và BD.<br><b>D.</b> Các điểm nằm trong tứ giác ABCD là E và F.<br>Khẳng định này <b>sai</b>. Nhìn vào hình vẽ, ta thấy điểm E nằm ngoài tứ giác ABCD <br><b>✅ Kết luận: Chọn đáp án D</b><br>",
                "key": "D",
                "isVideo": true,
                "score": 0,
                "order": 5,
                "fillKey": "",
                "yourKey": "",
                "isTested": false,
                "isBookmark": false,
                "liked": false,
                "questionScore": 0.5,
                "plans": [],
                "answerPlans": []
            },
            {
                "questionId": 21185524,
                "lessonId": 0,
                "a": "<img style = \"vertical-align:middle\" src= \"https://asset.moon.vn/new-latex/2025/10/7c9a58f3-afd7-49ed-98ae-d75ec3d14710.png\"/>",
                "b": "<img style = \"vertical-align:middle\" src= \"https://asset.moon.vn/new-latex/2025/10/31784082-7114-47e7-8ef2-65d35732414d.png\"/>",
                "c": "<img style = \"vertical-align:middle\" src= \"https://asset.moon.vn/new-latex/2025/10/08b37019-3a85-4a5f-bd66-bc2987de9ae0.png\"/>",
                "d": "<img style = \"vertical-align:middle\" src= \"https://asset.moon.vn/new-latex/2025/10/54d163e2-f955-4eeb-8766-445aa3d2a81d.png\"/>",
                "bookId": 1055475,
                "comments": 0,
                "bookmarks": 0,
                "likes": 0,
                "shares": 0,
                "typeId": 0,
                "questionText": "Cho tứ giác MNPQ, biết <img style = \"vertical-align:middle\" src= \"https://asset.moon.vn/new-latex/2025/10/6e881615-1036-4a67-abbd-5ffa19c27c31.png\"/><img style = \"vertical-align:middle\" src= \"https://asset.moon.vn/new-latex/2025/10/cf22e865-2da0-4b79-ae14-2cf93abe7431.png\"/><img style = \"vertical-align:middle\" src= \"https://asset.moon.vn/new-latex/2025/10/b375e226-5b06-4ea6-99c6-25c4934660b2.png\"/> Số đo góc N là",
                "answer": "🔍 <b>Phương pháp</b><br>Để tìm số đo góc N, ta sẽ sử dụng định lý về tổng bốn góc trong một tứ giác. Tổng số đo của bốn góc trong một tứ giác bất kỳ luôn bằng <b>360°</b>.<br>✍️ <b>Lời giải chi tiết</b><br>Theo định lý tổng các góc của một tứ giác, ta có:<br>M + N + P + Q = 360°<br>Thay số đo các góc đã biết vào biểu thức trên:<br>65° + N + 105° + 100° = 360°<br>(65° + 105° + 100°) + N = 360°<br>270° + N = 360°<br>N = 360° - 270°<br>N = 90°<br>✅ <b>Kết luận: Chọn đáp án B</b><br>",
                "key": "B",
                "isVideo": true,
                "score": 0,
                "order": 6,
                "fillKey": "",
                "yourKey": "",
                "isTested": false,
                "isBookmark": false,
                "liked": false,
                "questionScore": 0.5,
                "plans": [],
                "answerPlans": []
            },
            {
                "questionId": 21185527,
                "lessonId": 0,
                "a": "<img style = \"vertical-align:middle\" src= \"https://asset.moon.vn/new-latex/2025/10/ee758adb-7fcb-4ac9-8555-74a55708ed88.png\"/>",
                "b": "<img style = \"vertical-align:middle\" src= \"https://asset.moon.vn/new-latex/2025/10/d0512a4f-35b4-47ba-848c-29ec0483382f.png\"/>",
                "c": "<img style = \"vertical-align:middle\" src= \"https://asset.moon.vn/new-latex/2025/10/e4079329-3e10-42c2-b037-354ecc694727.png\"/>",
                "d": "<img style = \"vertical-align:middle\" src= \"https://asset.moon.vn/new-latex/2025/10/9a81ea5a-9db1-44e4-b492-a04ff0067d4d.png\"/>",
                "bookId": 1055476,
                "comments": 0,
                "bookmarks": 0,
                "likes": 0,
                "shares": 0,
                "typeId": 0,
                "questionText": "Cho tứ giác ABCD, biết <img style = \"vertical-align:middle\" src= \"https://asset.moon.vn/new-latex/2025/10/a3a2f45d-c353-4e37-a68b-3815fbc07b5b.png\"/> Số đo<img style = \"vertical-align:middle\" src= \"https://asset.moon.vn/new-latex/2025/10/754d73ea-543e-4fec-bb05-05ab0b251b68.png\"/> là",
                "answer": "🔍 <b>Phương pháp</b><br>Để tìm số đo góc D, ta sử dụng định lý về tổng bốn góc trong một tứ giác. Tổng số đo của bốn góc trong một tứ giác bất kỳ luôn bằng <b>360°</b>.<br>✍️ <b>Lời giải chi tiết</b><br>Theo định lý tổng các góc của một tứ giác, ta có:<br>A + B + C + D = 360°<br>Thay số đo các góc đã biết vào biểu thức trên:<br>80° + 65° + 110° + D = 360°<br>(80° + 65° + 110°) + D = 360°<br>255° + D = 360°<br>D = 360° - 255°<br>D = 105°<br>✅ <b>Kết luận: Chọn đáp án A</b><br>",
                "key": "A",
                "isVideo": true,
                "score": 0,
                "order": 7,
                "fillKey": "",
                "yourKey": "",
                "isTested": false,
                "isBookmark": false,
                "liked": false,
                "questionScore": 0.5,
                "plans": [],
                "answerPlans": []
            },
            {
                "questionId": 21185531,
                "lessonId": 0,
                "a": "<img style = \"vertical-align:middle\" src= \"https://asset.moon.vn/new-latex/2025/10/e4dd0dc3-944d-4221-b54c-33fc6a27fe64.png\"/>",
                "b": "<img style = \"vertical-align:middle\" src= \"https://asset.moon.vn/new-latex/2025/10/ca725b05-49fa-4551-b06f-d716fdb65d7d.png\"/>",
                "c": "<img style = \"vertical-align:middle\" src= \"https://asset.moon.vn/new-latex/2025/10/236e5ecb-4e04-4d38-8c73-bd6d9fff1a61.png\"/>",
                "d": "<img style = \"vertical-align:middle\" src= \"https://asset.moon.vn/new-latex/2025/10/d97c6a1c-03c7-4022-ab35-ef2104a54157.png\"/>",
                "bookId": 1055477,
                "comments": 5,
                "bookmarks": 3,
                "likes": 0,
                "shares": 0,
                "typeId": 0,
                "questionText": "Cho tứ giác ABCD có <img style = \"vertical-align:middle\" src= \"https://asset.moon.vn/new-latex/2025/10/3eb86634-a458-4bf2-9033-9b7cebad2887.png\"/> Khi đó số đo của góc C bằng",
                "answer": "<b>🔍 Phương pháp</b><br>Để tìm số đo góc C, chúng ta sẽ làm theo các bước sau:<br>1. Sử dụng định lý tổng bốn góc của một tứ giác (luôn bằng <img style = \"vertical-align:middle\" src= \"https://asset.moon.vn/new-latex/2025/10/f96c1ff2-6ecb-4b61-a618-fa0dbf24d560.png\"/>) để thiết lập một phương trình.<br>2. Tìm tổng của hai góc chưa biết là <img style = \"vertical-align:middle\" src= \"https://asset.moon.vn/new-latex/2025/10/68cafc9e-e1b3-43c1-902d-0cd90ec8d645.png\"/> và <img style = \"vertical-align:middle\" src= \"https://asset.moon.vn/new-latex/2025/10/c46ac99e-0d43-4fe9-8b32-d37384fe056f.png\"/>.<br>3. Sử dụng mối quan hệ đã cho <img style = \"vertical-align:middle\" src= \"https://asset.moon.vn/new-latex/2025/10/26393d5b-c0c2-43f9-8690-cb849680eb2c.png\"/> để thay thế và giải phương trình tìm ra số đo của <img style = \"vertical-align:middle\" src= \"https://asset.moon.vn/new-latex/2025/10/b57d7109-14f0-4184-af74-29e98145903d.png\"/>.<br>4. Từ số đo của <img style = \"vertical-align:middle\" src= \"https://asset.moon.vn/new-latex/2025/10/316f9f20-8baa-47e0-92ad-fed7a18e276d.png\"/>, tính ra số đo của <img style = \"vertical-align:middle\" src= \"https://asset.moon.vn/new-latex/2025/10/f099c694-f040-407e-8841-c680958accec.png\"/>.<br><b>✍️ Lời giải chi tiết</b><br>Theo định lý tổng các góc của một tứ giác, ta có <img style = \"vertical-align:middle\" src= \"https://asset.moon.vn/new-latex/2025/10/d8f08cfc-5f5a-4673-8f07-ccbe55a093c6.png\"/>.<br>Thay số đo các góc đã biết vào biểu thức:<br><img style = \"vertical-align:middle\" src= \"https://asset.moon.vn/new-latex/2025/10/01e403ae-2db6-444c-a545-a390689ea30e.png\"/><br><img style = \"vertical-align:middle\" src= \"https://asset.moon.vn/new-latex/2025/10/d5c50be7-e901-4e6f-91e6-fc048d7c6937.png\"/><br>Suy ra tổng của hai góc <img style = \"vertical-align:middle\" src= \"https://asset.moon.vn/new-latex/2025/10/bf51ec97-59ef-45e9-8f25-030bb46474f8.png\"/> và <img style = \"vertical-align:middle\" src= \"https://asset.moon.vn/new-latex/2025/10/7d2cb8c0-3c09-489b-a0e7-658c68627437.png\"/>:<br><img style = \"vertical-align:middle\" src= \"https://asset.moon.vn/new-latex/2025/10/f8caccfb-1662-4df6-8093-28b4a82b2a54.png\"/><br>Theo đề bài, ta có <img style = \"vertical-align:middle\" src= \"https://asset.moon.vn/new-latex/2025/10/ea8f93cb-cfdc-4892-8c4f-acabf86c6aae.png\"/>. Thay vào phương trình trên:<br><img style = \"vertical-align:middle\" src= \"https://asset.moon.vn/new-latex/2025/10/dd571733-470d-4289-ac34-dc5a92409841.png\"/><br><img style = \"vertical-align:middle\" src= \"https://asset.moon.vn/new-latex/2025/10/313de128-baf2-4059-b194-0749f1d55728.png\"/><br><img style = \"vertical-align:middle\" src= \"https://asset.moon.vn/new-latex/2025/10/0bcb0c20-e9fc-4873-8bd2-6f767acd812e.png\"/><br>Cuối cùng, ta tìm số đo góc C:<br><img style = \"vertical-align:middle\" src= \"https://asset.moon.vn/new-latex/2025/10/74818a29-0e1a-4681-94ef-538dbbb63131.png\"/><br><b>✅ Kết luận: Chọn đáp án C</b><br>",
                "key": "C",
                "isVideo": true,
                "score": 0,
                "order": 8,
                "fillKey": "",
                "yourKey": "",
                "isTested": false,
                "isBookmark": false,
                "liked": false,
                "questionScore": 0.5,
                "plans": [],
                "answerPlans": []
            },
            {
                "questionId": 21185536,
                "lessonId": 0,
                "a": "<img style = \"vertical-align:middle\" src= \"https://asset.moon.vn/new-latex/2025/10/f54467e8-6c72-447b-a058-4d00348eb666.png\"/>",
                "b": "<img style = \"vertical-align:middle\" src= \"https://asset.moon.vn/new-latex/2025/10/dcb8df38-36e4-44fa-95f9-4fd5030cf29a.png\"/>",
                "c": "<img style = \"vertical-align:middle\" src= \"https://asset.moon.vn/new-latex/2025/10/d92008d5-ec68-4ead-a5c0-e80d2a6d6e8c.png\"/>",
                "d": "<img style = \"vertical-align:middle\" src= \"https://asset.moon.vn/new-latex/2025/10/4e68918b-38df-4ea9-b95d-a00901c73dd3.png\"/>",
                "bookId": 1055478,
                "comments": 0,
                "bookmarks": 0,
                "likes": 0,
                "shares": 0,
                "typeId": 0,
                "questionText": "Cho tứ giác ABCD, biết <img style = \"vertical-align:middle\" src= \"https://asset.moon.vn/new-latex/2025/10/04bc35fa-af82-4de1-b865-2a7732fd599d.png\"/> <img style = \"vertical-align:middle\" src= \"https://asset.moon.vn/new-latex/2025/10/ecae7f36-0ddf-4fc1-b720-dcdff0864ec2.png\"/> <img style = \"vertical-align:middle\" src= \"https://asset.moon.vn/new-latex/2025/10/9c7595e1-790f-4e4f-8f26-2c5df7aa7b10.png\"/> Khi đó số đo góc C là<br><img src=\"https://asset.moon.vn/img/chat/large/2025/10/5c8394d2-1364-4e0c-81e7-00b7f03077b7.jpg\" data-filename=\"\" style=\"max-width: 600px; height: auto;\">",
                "answer": "<b>🔍 Phương pháp</b><br>Để tìm số đo góc C, ta sử dụng định lý về tổng bốn góc trong một tứ giác. Tổng số đo của bốn góc trong một tứ giác bất kỳ luôn bằng <img style = \"vertical-align:middle\" src= \"https://asset.moon.vn/new-latex/2025/10/de1ed328-76ff-4732-9f43-a44719eac2ef.png\"/>.<br><b>✍️ Lời giải chi tiết</b><br>Theo định lý tổng các góc của một tứ giác, ta có <img style = \"vertical-align:middle\" src= \"https://asset.moon.vn/new-latex/2025/10/ab59e6bd-8d24-48e6-814f-904e6aac2404.png\"/>.<br>Thay số đo các góc đã biết từ hình vẽ và đề bài vào biểu thức:<br><img style = \"vertical-align:middle\" src= \"https://asset.moon.vn/new-latex/2025/10/600a4464-b41b-4fcc-ba12-3fdad99d9978.png\"/><br><img style = \"vertical-align:middle\" src= \"https://asset.moon.vn/new-latex/2025/10/e491166d-ad2f-42de-b438-acda55df46ca.png\"/><br><img style = \"vertical-align:middle\" src= \"https://asset.moon.vn/new-latex/2025/10/6970860d-cec8-4825-9388-e75d4fa9f800.png\"/><br><img style = \"vertical-align:middle\" src= \"https://asset.moon.vn/new-latex/2025/10/6e1a3e89-97e6-414c-a97c-32ae99ae4c6a.png\"/><br><img style = \"vertical-align:middle\" src= \"https://asset.moon.vn/new-latex/2025/10/1f5fdd35-19d4-4c35-9040-592586323fa1.png\"/><br><b>✅ Kết luận: Chọn đáp án A</b><br>",
                "key": "A",
                "isVideo": true,
                "score": 0,
                "order": 9,
                "fillKey": "",
                "yourKey": "",
                "isTested": false,
                "isBookmark": false,
                "liked": false,
                "questionScore": 0.5,
                "plans": [],
                "answerPlans": []
            },
            {
                "questionId": 21185537,
                "lessonId": 0,
                "a": "<img style = \"vertical-align:middle\" src= \"https://asset.moon.vn/new-latex/2025/10/135f3eaf-dbec-4e2a-ba5b-e5de8d85add4.png\"/>",
                "b": "<img style = \"vertical-align:middle\" src= \"https://asset.moon.vn/new-latex/2025/10/20bd6eee-1ce1-4c01-b8e5-3d5127604254.png\"/>",
                "c": "<img style = \"vertical-align:middle\" src= \"https://asset.moon.vn/new-latex/2025/10/eab2b677-9e43-4b38-b116-763c7c0b635d.png\"/>",
                "d": "<img style = \"vertical-align:middle\" src= \"https://asset.moon.vn/new-latex/2025/10/00884d13-1366-47de-9943-0a5a54868108.png\"/>",
                "bookId": 1055479,
                "comments": 0,
                "bookmarks": 5,
                "likes": 0,
                "shares": 0,
                "typeId": 0,
                "questionText": "Cho tứ giác <img style = \"vertical-align:middle\" src= \"https://asset.moon.vn/new-latex/2025/10/6eba56cb-cf7a-4ccb-84a6-2f51385591dd.png\"/> có <img style = \"vertical-align:middle\" src= \"https://asset.moon.vn/new-latex/2025/10/0419f81e-78a3-46a6-a114-1e7802dd99f9.png\"/> <img style = \"vertical-align:middle\" src= \"https://asset.moon.vn/new-latex/2025/10/67179d29-9cd5-412d-a14e-9235758e57a4.png\"/> <img style = \"vertical-align:middle\" src= \"https://asset.moon.vn/new-latex/2025/10/1a12a768-c910-4f5f-91fd-00f4db533c61.png\"/> Khi đó số đo của góc <img style = \"vertical-align:middle\" src= \"https://asset.moon.vn/new-latex/2025/10/3a11e480-8ba4-4fab-8de1-aeda6b84b428.png\"/> bằng",
                "answer": "<b>🔍 Phương pháp</b><br>Để tìm số đo góc D, chúng ta sẽ làm theo các bước sau:<br>1. Sử dụng định lý tổng bốn góc của một tứ giác (luôn bằng <img style = \"vertical-align:middle\" src= \"https://asset.moon.vn/new-latex/2025/10/e101060f-ddb9-4140-b0dd-080412467a21.png\"/>) để thiết lập một phương trình.<br>2. Tìm tổng của hai góc chưa biết là <img style = \"vertical-align:middle\" src= \"https://asset.moon.vn/new-latex/2025/10/25780900-be35-47de-9db1-a222ff7ad14c.png\"/> và <img style = \"vertical-align:middle\" src= \"https://asset.moon.vn/new-latex/2025/10/5d96b61d-6c92-4d9a-94b0-eb288a516643.png\"/>.<br>3. Sử dụng mối quan hệ đã cho <img style = \"vertical-align:middle\" src= \"https://asset.moon.vn/new-latex/2025/10/c736778b-54be-480b-a0e8-a7e5ad077a72.png\"/> để thay thế và giải phương trình tìm ra số đo của <img style = \"vertical-align:middle\" src= \"https://asset.moon.vn/new-latex/2025/10/2c8c6970-dc07-4c8e-aa29-b3f384289fd4.png\"/>.<br><b>✍️ Lời giải chi tiết</b><br>Theo định lý tổng các góc của một tứ giác, ta có <img style = \"vertical-align:middle\" src= \"https://asset.moon.vn/new-latex/2025/10/3e4b30dc-f1b4-488c-9636-3a2044930eb6.png\"/>.<br>Thay số đo các góc đã biết vào biểu thức:<br><img style = \"vertical-align:middle\" src= \"https://asset.moon.vn/new-latex/2025/10/d7db9e31-38d6-47fd-a459-ab3622f37612.png\"/><br><img style = \"vertical-align:middle\" src= \"https://asset.moon.vn/new-latex/2025/10/ec4623cd-3038-4396-8881-e9c0b5d00bb6.png\"/><br>Suy ra tổng của hai góc <img style = \"vertical-align:middle\" src= \"https://asset.moon.vn/new-latex/2025/10/9fcfcb45-dda8-40e3-8453-564c2c4d1a68.png\"/> và <img style = \"vertical-align:middle\" src= \"https://asset.moon.vn/new-latex/2025/10/56984421-bdde-4848-9cfd-6cbdb15bf5ab.png\"/>:<br><img style = \"vertical-align:middle\" src= \"https://asset.moon.vn/new-latex/2025/10/a51909ef-27ab-4285-8dba-7e31503339b9.png\"/><br><img style = \"vertical-align:middle\" src= \"https://asset.moon.vn/new-latex/2025/10/40e4bb6d-37cc-4eed-a2b1-2b89b296d297.png\"/><br>Theo đề bài, ta có <img style = \"vertical-align:middle\" src= \"https://asset.moon.vn/new-latex/2025/10/177b328f-f2e9-4d80-82b1-33dfe8fef120.png\"/>. Thay vào phương trình trên:<br><img style = \"vertical-align:middle\" src= \"https://asset.moon.vn/new-latex/2025/10/99d89467-61df-4659-a31a-58fd0c2a3475.png\"/><br><img style = \"vertical-align:middle\" src= \"https://asset.moon.vn/new-latex/2025/10/7a5900a4-dcf1-47dc-b5f3-12f63d26e1e8.png\"/><br><img style = \"vertical-align:middle\" src= \"https://asset.moon.vn/new-latex/2025/10/5e81c33f-d2a5-4175-948c-e4395e914f42.png\"/><br><img style = \"vertical-align:middle\" src= \"https://asset.moon.vn/new-latex/2025/10/4822a0b7-98ab-4a84-8314-72a7d290496e.png\"/><br><b>✅ Kết luận: Chọn đáp án A</b><br>",
                "key": "A",
                "isVideo": true,
                "score": 0,
                "order": 10,
                "fillKey": "",
                "yourKey": "",
                "isTested": false,
                "isBookmark": false,
                "liked": false,
                "questionScore": 0.5,
                "plans": [],
                "answerPlans": []
            },
            {
                "questionId": 21185552,
                "lessonId": 0,
                "a": "<img style = \"vertical-align:middle\" src= \"https://asset.moon.vn/new-latex/2025/10/7263a4b5-ccc4-4654-b92f-6ee59fdb44b3.png\"/>",
                "b": "<img style = \"vertical-align:middle\" src= \"https://asset.moon.vn/new-latex/2025/10/c392cd9f-3ba7-427f-b97b-8446f8a404c1.png\"/>",
                "c": "<img style = \"vertical-align:middle\" src= \"https://asset.moon.vn/new-latex/2025/10/5d037c6d-566e-42d5-a5ce-d165508184ae.png\"/>",
                "d": "<img style = \"vertical-align:middle\" src= \"https://asset.moon.vn/new-latex/2025/10/427edd93-e0a7-49e3-9ef4-0e57d4f18377.png\"/>",
                "bookId": 1055480,
                "comments": 0,
                "bookmarks": 0,
                "likes": 0,
                "shares": 0,
                "typeId": 0,
                "questionText": "Cho tứ giác <img style = \"vertical-align:middle\" src= \"https://asset.moon.vn/new-latex/2025/10/01320402-31e4-44d5-9f2b-826c1fd3b30b.png\"/> có <img style = \"vertical-align:middle\" src= \"https://asset.moon.vn/new-latex/2025/10/19d76b33-22cb-45f6-bfe5-eb6f9eee9838.png\"/> <img style = \"vertical-align:middle\" src= \"https://asset.moon.vn/new-latex/2025/10/11ee9890-d66b-48d8-8a16-354c2b11a936.png\"/> <img style = \"vertical-align:middle\" src= \"https://asset.moon.vn/new-latex/2025/10/36e67803-a4ec-4948-8f89-0c5c6b90debb.png\"/> Số đo góc <img style = \"vertical-align:middle\" src= \"https://asset.moon.vn/new-latex/2025/10/3e27280f-9d38-4b38-8684-612b0eacbaca.png\"/> bằng",
                "answer": "<b>🔍 Phương pháp</b><br>Để tìm số đo góc B, ta sử dụng định lý về tổng bốn góc trong một tứ giác. Tổng số đo của bốn góc trong một tứ giác bất kỳ luôn bằng <img style = \"vertical-align:middle\" src= \"https://asset.moon.vn/new-latex/2025/10/1d66c6ff-01d8-4675-bcd8-eafe751e4bf5.png\"/>.<br><b>✍️ Lời giải chi tiết</b><br>Theo định lý tổng các góc của một tứ giác, ta có <img style = \"vertical-align:middle\" src= \"https://asset.moon.vn/new-latex/2025/10/bf2bb02a-3b81-49db-a9f9-106d943d7e4e.png\"/>.<br>Thay số đo các góc đã biết vào biểu thức trên:<br><img style = \"vertical-align:middle\" src= \"https://asset.moon.vn/new-latex/2025/10/58a237b5-4c88-4a7c-ac4a-8f8ef52a0632.png\"/><br><img style = \"vertical-align:middle\" src= \"https://asset.moon.vn/new-latex/2025/10/4fdc6ce2-31c5-4123-8163-ebbc903bc364.png\"/><br><img style = \"vertical-align:middle\" src= \"https://asset.moon.vn/new-latex/2025/10/2b5ffd55-4ab5-496e-a53d-942119c239da.png\"/><br><img style = \"vertical-align:middle\" src= \"https://asset.moon.vn/new-latex/2025/10/68fd48c8-7b84-4aeb-a3fa-2096410ecd65.png\"/><br><img style = \"vertical-align:middle\" src= \"https://asset.moon.vn/new-latex/2025/10/08007080-868e-4d51-bc13-441ea05c2a99.png\"/><br><b>✅ Kết luận: Chọn đáp án D</b><br>",
                "key": "D",
                "isVideo": true,
                "score": 0,
                "order": 11,
                "fillKey": "",
                "yourKey": "",
                "isTested": false,
                "isBookmark": false,
                "liked": false,
                "questionScore": 0.5,
                "plans": [],
                "answerPlans": []
            },
            {
                "questionId": 21185555,
                "lessonId": 0,
                "a": "<img style = \"vertical-align:middle\" src= \"https://asset.moon.vn/new-latex/2025/10/f02ccba7-19c3-419c-8c45-3725f28b525d.png\"/>",
                "b": "<img style = \"vertical-align:middle\" src= \"https://asset.moon.vn/new-latex/2025/10/8eb75cd6-5c82-4609-bd9f-3049c8b23e61.png\"/>",
                "c": "<img style = \"vertical-align:middle\" src= \"https://asset.moon.vn/new-latex/2025/10/81118372-a50e-4c59-bf2b-c2d134f5c86c.png\"/>",
                "d": "<img style = \"vertical-align:middle\" src= \"https://asset.moon.vn/new-latex/2025/10/3bd193d2-b4bf-47bb-b5bc-1b43174fdf58.png\"/>",
                "bookId": 1055481,
                "comments": 0,
                "bookmarks": 0,
                "likes": 0,
                "shares": 0,
                "typeId": 0,
                "questionText": "Tứ giác có tổng ba góc bằng <img style = \"vertical-align:middle\" src= \"https://asset.moon.vn/new-latex/2025/10/8ee74124-0ced-4384-b213-33fd6cf9faaf.png\"/> thì góc còn lại bằng",
                "answer": "<b>🔍 Phương pháp</b><br>Để tìm số đo góc còn lại, ta sử dụng định lý về tổng bốn góc trong một tứ giác. Tổng số đo của bốn góc trong một tứ giác bất kỳ luôn bằng <img style = \"vertical-align:middle\" src= \"https://asset.moon.vn/new-latex/2025/10/9698b1d0-7c5c-41a7-87ef-b8d36f18ff14.png\"/>.<br><b>✍️ Lời giải chi tiết</b><br>Gọi 4 góc của tứ giác là <img style = \"vertical-align:middle\" src= \"https://asset.moon.vn/new-latex/2025/10/dc80be49-c0c7-4f4d-9171-5c94a0e97c93.png\"/> và <img style = \"vertical-align:middle\" src= \"https://asset.moon.vn/new-latex/2025/10/e624e60f-92b6-402f-b2e2-91ca6ec316a4.png\"/>.<br>Theo định lý tổng các góc của một tứ giác, ta có <img style = \"vertical-align:middle\" src= \"https://asset.moon.vn/new-latex/2025/10/30591724-f76a-4b76-bde8-536ef6211c0d.png\"/>.<br>Theo đề bài, tổng của ba góc bằng <img style = \"vertical-align:middle\" src= \"https://asset.moon.vn/new-latex/2025/10/b0c79b29-8b49-42cd-98ea-84581f4c4cf6.png\"/>. Giả sử: <img style = \"vertical-align:middle\" src= \"https://asset.moon.vn/new-latex/2025/10/e7a304aa-e1f4-4304-85aa-298769d44a53.png\"/>.<br>Để tìm góc còn lại (là <img style = \"vertical-align:middle\" src= \"https://asset.moon.vn/new-latex/2025/10/605c91ab-48e8-4bf0-b101-480e077668a6.png\"/>), ta thay giá trị này vào biểu thức tổng:<br><img style = \"vertical-align:middle\" src= \"https://asset.moon.vn/new-latex/2025/10/309882b8-0614-4348-b61d-a8ddd04d3abe.png\"/><br>Suy ra số đo góc <img style = \"vertical-align:middle\" src= \"https://asset.moon.vn/new-latex/2025/10/43816633-1de3-42a4-98bb-23491f9bc854.png\"/>:<br><img style = \"vertical-align:middle\" src= \"https://asset.moon.vn/new-latex/2025/10/a9ad6c5c-e701-439f-b2ca-c04e0241695c.png\"/><br><img style = \"vertical-align:middle\" src= \"https://asset.moon.vn/new-latex/2025/10/7315fe04-e701-4953-95a5-24992c6a6b28.png\"/><br><b>✅ Kết luận: Chọn đáp án C</b><br>",
                "key": "C",
                "isVideo": true,
                "score": 0,
                "order": 12,
                "fillKey": "",
                "yourKey": "",
                "isTested": false,
                "isBookmark": false,
                "liked": false,
                "questionScore": 0.5,
                "plans": [],
                "answerPlans": []
            },
            {
                "questionId": 21185561,
                "lessonId": 0,
                "a": "<img style = \"vertical-align:middle\" src= \"https://asset.moon.vn/new-latex/2025/10/3bafe0c6-df0e-4c7a-b8e9-5d7308abda1a.png\"/>",
                "b": "<img style = \"vertical-align:middle\" src= \"https://asset.moon.vn/new-latex/2025/10/a207e7ca-25df-468a-b9a9-9c23c7eb796c.png\"/>",
                "c": "<img style = \"vertical-align:middle\" src= \"https://asset.moon.vn/new-latex/2025/10/e2323e93-4baa-458b-a1fb-7a57f50d4367.png\"/>",
                "d": "<img style = \"vertical-align:middle\" src= \"https://asset.moon.vn/new-latex/2025/10/1b5cf260-da60-4efe-af0c-338c2ec4a2c5.png\"/>",
                "bookId": 1055482,
                "comments": 4,
                "bookmarks": 0,
                "likes": 0,
                "shares": 0,
                "typeId": 0,
                "questionText": "Tứ giác ABCD có <img style = \"vertical-align:middle\" src= \"https://asset.moon.vn/new-latex/2025/10/c826fbbf-3bfd-41fa-89a7-9f9963bef646.png\"/> <img style = \"vertical-align:middle\" src= \"https://asset.moon.vn/new-latex/2025/10/d07eeae9-0fd9-4579-8b4e-04d8ca94d148.png\"/> <img style = \"vertical-align:middle\" src= \"https://asset.moon.vn/new-latex/2025/10/52b7fda9-8db2-430f-901c-d5c307766840.png\"/> Số đo góc <img style = \"vertical-align:middle\" src= \"https://asset.moon.vn/new-latex/2025/10/72c74f16-0a39-4616-b953-266679b49f4d.png\"/> là",
                "answer": "<b>🔍 Phương pháp</b><br>Để tìm số đo góc D, ta sử dụng định lý về tổng bốn góc trong một tứ giác. Tổng số đo của bốn góc trong một tứ giác bất kỳ luôn bằng <img style = \"vertical-align:middle\" src= \"https://asset.moon.vn/new-latex/2025/10/04cfa046-6835-4433-b253-3957a88385f0.png\"/>.<br><b>✍️ Lời giải chi tiết</b><br>Theo định lý tổng các góc của một tứ giác, ta có <img style = \"vertical-align:middle\" src= \"https://asset.moon.vn/new-latex/2025/10/1a069963-2d6d-4a0f-b626-d68af5baec12.png\"/>.<br>Thay số đo các góc đã biết vào biểu thức trên:<br><img style = \"vertical-align:middle\" src= \"https://asset.moon.vn/new-latex/2025/10/b4f2e311-ef9f-4471-b422-499f429219e0.png\"/><br><img style = \"vertical-align:middle\" src= \"https://asset.moon.vn/new-latex/2025/10/6aaadbb3-e6f4-4aa3-8286-8e4ac367f260.png\"/><br><img style = \"vertical-align:middle\" src= \"https://asset.moon.vn/new-latex/2025/10/0752bb21-bc81-4a00-bd36-18dd5134fa5b.png\"/><br><img style = \"vertical-align:middle\" src= \"https://asset.moon.vn/new-latex/2025/10/f6149c61-40b5-46ed-9309-6ea501be6e5d.png\"/><br><img style = \"vertical-align:middle\" src= \"https://asset.moon.vn/new-latex/2025/10/cd23d7a1-8019-4f70-98a2-c0c4a8380d73.png\"/><br><b>✅ Kết luận: Chọn đáp án B</b><br>",
                "key": "B",
                "isVideo": true,
                "score": 0,
                "order": 13,
                "fillKey": "",
                "yourKey": "",
                "isTested": false,
                "isBookmark": false,
                "liked": false,
                "questionScore": 0.5,
                "plans": [],
                "answerPlans": []
            },
            {
                "questionId": 21185575,
                "lessonId": 0,
                "a": "<img style = \"vertical-align:middle\" src= \"https://asset.moon.vn/new-latex/2025/10/f843e9a3-369c-4bb4-b383-d076a3febf5d.png\"/>",
                "b": "<img style = \"vertical-align:middle\" src= \"https://asset.moon.vn/new-latex/2025/10/0e7fe870-cef9-418d-9b54-fae3e0eb927f.png\"/>",
                "c": "<img style = \"vertical-align:middle\" src= \"https://asset.moon.vn/new-latex/2025/10/9e9c7ba8-019c-41a4-9c33-26c95e599fde.png\"/>",
                "d": "<img style = \"vertical-align:middle\" src= \"https://asset.moon.vn/new-latex/2025/10/2cada618-cfa8-494a-96e5-00ec9e972adb.png\"/>",
                "bookId": 1055483,
                "comments": 1,
                "bookmarks": 0,
                "likes": 0,
                "shares": 0,
                "typeId": 0,
                "questionText": "Cho tứ giác ABCD có <img style = \"vertical-align:middle\" src= \"https://asset.moon.vn/new-latex/2025/10/bf82238d-38bd-4fbb-9cc9-b96c8e79aaa4.png\"/> Số đo góc D là",
                "answer": "<b>🔍 Phương pháp</b><br>Để tìm số đo góc D, ta sử dụng định lý về tổng bốn góc trong một tứ giác. Tổng số đo của bốn góc trong một tứ giác bất kỳ luôn bằng <img style = \"vertical-align:middle\" src= \"https://asset.moon.vn/new-latex/2025/10/dcadd568-738c-4c34-9cdd-39441683312a.png\"/>.<br><b>✍️ Lời giải chi tiết</b><br>Theo định lý tổng các góc của một tứ giác, ta có <img style = \"vertical-align:middle\" src= \"https://asset.moon.vn/new-latex/2025/10/242dae85-85e7-4b1b-948b-5f2689b413f6.png\"/>.<br>Thay số đo các góc đã biết vào biểu thức trên:<br><img style = \"vertical-align:middle\" src= \"https://asset.moon.vn/new-latex/2025/10/ea4571c5-0468-4bfc-ad84-03219637555e.png\"/><br><img style = \"vertical-align:middle\" src= \"https://asset.moon.vn/new-latex/2025/10/56e6fa02-74cd-430d-851a-e679db665bd2.png\"/><br><img style = \"vertical-align:middle\" src= \"https://asset.moon.vn/new-latex/2025/10/be4f36f3-e015-48f6-9e66-3014d32056c3.png\"/><br><img style = \"vertical-align:middle\" src= \"https://asset.moon.vn/new-latex/2025/10/070ceeb1-6a0e-43e6-94a1-cb8087089128.png\"/><br><img style = \"vertical-align:middle\" src= \"https://asset.moon.vn/new-latex/2025/10/687fe8d2-14e7-4843-8ab4-d9cf51c0305b.png\"/><br><b>✅ Kết luận: Chọn đáp án B</b><br>",
                "key": "B",
                "isVideo": true,
                "score": 0,
                "order": 14,
                "fillKey": "",
                "yourKey": "",
                "isTested": false,
                "isBookmark": false,
                "liked": false,
                "questionScore": 0.5,
                "plans": [],
                "answerPlans": []
            },
            {
                "questionId": 21185583,
                "lessonId": 0,
                "a": "<img style = \"vertical-align:middle\" src= \"https://asset.moon.vn/new-latex/2025/10/d9cc6846-0267-43c2-9027-c067f787e9c7.png\"/>",
                "b": "<img style = \"vertical-align:middle\" src= \"https://asset.moon.vn/new-latex/2025/10/23e74f3d-db23-4a78-a93a-3fe935336735.png\"/>",
                "c": "<img style = \"vertical-align:middle\" src= \"https://asset.moon.vn/new-latex/2025/10/fc53634e-7694-44d9-80d4-ecdfc2b05abf.png\"/>",
                "d": "<img style = \"vertical-align:middle\" src= \"https://asset.moon.vn/new-latex/2025/10/8adedefd-1eef-429f-b78f-bad60aabb4da.png\"/>",
                "bookId": 1055484,
                "comments": 2,
                "bookmarks": 1,
                "likes": 0,
                "shares": 0,
                "typeId": 0,
                "questionText": "Một hồ bơi có dạng tứ giác ABCD được mô tả như hình vẽ. Biết AC là tia phân giác góc <img style = \"vertical-align:middle\" src= \"https://asset.moon.vn/new-latex/2025/10/e5dd5557-5d5e-4850-a64d-0ba0b0e6a4a0.png\"/> và <img style = \"vertical-align:middle\" src= \"https://asset.moon.vn/new-latex/2025/10/a6f72ae6-1d6b-4010-bbaa-3301015e8d80.png\"/> Số đo góc <img style = \"vertical-align:middle\" src= \"https://asset.moon.vn/new-latex/2025/10/24dd1ddc-7a7f-422a-acef-2d43d6dffd4f.png\"/> là<br><img src=\"https://asset.moon.vn/img/chat/large/2025/10/ca1f7fde-99f0-4533-aa12-66f56b31e5fa.jpg\" data-filename=\"\" style=\"max-width: 600px; height: auto;\">",
                "answer": "<b>🔍 Phương pháp</b><br>Để tìm số đo góc <img style = \"vertical-align:middle\" src= \"https://asset.moon.vn/new-latex/2025/10/ee2d785b-941b-4579-9228-cc9176ebe0f8.png\"/>, ta sẽ thực hiện theo hai bước:<br>1. <b>Tìm số đo góc <img style = \"vertical-align:middle\" src= \"https://asset.moon.vn/new-latex/2025/10/4a5381d4-e8f1-4e3b-a3e2-21ca99232cdc.png\"/>:</b> Sử dụng giả thiết \"AC là tia phân giác của góc <img style = \"vertical-align:middle\" src= \"https://asset.moon.vn/new-latex/2025/10/1c7207f4-b5e3-495d-ade9-891b3a1f6499.png\"/>\" và số đo <img style = \"vertical-align:middle\" src= \"https://asset.moon.vn/new-latex/2025/10/ab3b3e3c-6f2a-4e2e-8992-56780b4060bf.png\"/> để tìm số đo của toàn bộ góc <img style = \"vertical-align:middle\" src= \"https://asset.moon.vn/new-latex/2025/10/0d79dbc1-b728-49c0-9cb2-6d7370e15d0b.png\"/>.<br>2. <b>Tìm số đo góc <img style = \"vertical-align:middle\" src= \"https://asset.moon.vn/new-latex/2025/10/d099bf36-004d-48e0-93dd-9795bbab4bad.png\"/>:</b> Sử dụng định lý về tổng bốn góc của một tứ giác (luôn bằng <img style = \"vertical-align:middle\" src= \"https://asset.moon.vn/new-latex/2025/10/b8f7c28d-4be4-4e5f-94f4-a4e0942df2dc.png\"/>) để tìm số đo góc còn lại.<br><b>✍️ Lời giải chi tiết</b><br><b>Bước 1: Tìm số đo góc <img style = \"vertical-align:middle\" src= \"https://asset.moon.vn/new-latex/2025/10/46ba01fc-135d-4e3c-851f-ddc32f1b5887.png\"/> (góc A)</b><br>Vì AC là tia phân giác của góc <img style = \"vertical-align:middle\" src= \"https://asset.moon.vn/new-latex/2025/10/32b521a2-1e3c-4098-9293-b1100f40bc95.png\"/>, nên ta có <img style = \"vertical-align:middle\" src= \"https://asset.moon.vn/new-latex/2025/10/078ad6bd-9ce3-428d-b8d0-1f60176440f3.png\"/>.<br>Theo đề bài, <img style = \"vertical-align:middle\" src= \"https://asset.moon.vn/new-latex/2025/10/1fbe0436-ac47-42ea-a896-ba6b68eb2f8a.png\"/>, suy ra <img style = \"vertical-align:middle\" src= \"https://asset.moon.vn/new-latex/2025/10/ad24ab43-11a6-4e25-81eb-0db7059201bb.png\"/>.<br>Vậy số đo của góc <img style = \"vertical-align:middle\" src= \"https://asset.moon.vn/new-latex/2025/10/faaa7b6e-ab2a-4564-8f83-33c302717897.png\"/> là <img style = \"vertical-align:middle\" src= \"https://asset.moon.vn/new-latex/2025/10/1a77874d-bcd6-441b-9eaa-b1c4bd4b3952.png\"/>.<br><b>Bước 2: Tìm số đo góc <img style = \"vertical-align:middle\" src= \"https://asset.moon.vn/new-latex/2025/10/8a06bbd9-cd25-4cb8-9c98-6f6e0848904e.png\"/> (góc C)</b><br>Theo định lý tổng các góc của một tứ giác, ta có <img style = \"vertical-align:middle\" src= \"https://asset.moon.vn/new-latex/2025/10/126af0c7-4e67-4c16-a97d-9b9796654942.png\"/>.<br>Từ hình vẽ, <img style = \"vertical-align:middle\" src= \"https://asset.moon.vn/new-latex/2025/10/98dd5ea6-7c9d-46cf-bc1d-7d136afaaff4.png\"/> và <img style = \"vertical-align:middle\" src= \"https://asset.moon.vn/new-latex/2025/10/3870b0d9-7ef0-4f13-a224-5861d169d6b3.png\"/>.<br>Thay các giá trị đã biết vào biểu thức:<br><img style = \"vertical-align:middle\" src= \"https://asset.moon.vn/new-latex/2025/10/3db41b87-aca7-497b-942f-2a5fca859706.png\"/><br><img style = \"vertical-align:middle\" src= \"https://asset.moon.vn/new-latex/2025/10/e0e74cbe-d4ca-4c4b-809a-a50879de94e8.png\"/><br><img style = \"vertical-align:middle\" src= \"https://asset.moon.vn/new-latex/2025/10/577a40f0-775f-40ea-ab73-41a97663377a.png\"/><br><img style = \"vertical-align:middle\" src= \"https://asset.moon.vn/new-latex/2025/10/0db3c9f4-0720-43f1-b1c0-a59ab82ce589.png\"/><br><img style = \"vertical-align:middle\" src= \"https://asset.moon.vn/new-latex/2025/10/ba84ed64-2af3-4158-87e2-ba03061c7786.png\"/><br><b>✅ Kết luận: Chọn đáp án A</b><br>",
                "key": "A",
                "isVideo": true,
                "score": 0,
                "order": 15,
                "fillKey": "",
                "yourKey": "",
                "isTested": false,
                "isBookmark": false,
                "liked": false,
                "questionScore": 0.5,
                "plans": [],
                "answerPlans": []
            },
            {
                "questionId": 21185598,
                "lessonId": 0,
                "a": "<img style = \"vertical-align:middle\" src= \"https://asset.moon.vn/new-latex/2025/10/d50b3d16-5e09-4e73-836f-c200e9aa740c.png\"/>",
                "b": "<img style = \"vertical-align:middle\" src= \"https://asset.moon.vn/new-latex/2025/10/10fdd339-bf36-4729-888a-50e7aa862e37.png\"/>",
                "c": "<img style = \"vertical-align:middle\" src= \"https://asset.moon.vn/new-latex/2025/10/9f6d7f25-c119-47df-bb41-6fbcf68fc15d.png\"/>",
                "d": "<img style = \"vertical-align:middle\" src= \"https://asset.moon.vn/new-latex/2025/10/1b736553-daef-43e0-ab2e-1db47a0bc36f.png\"/>",
                "bookId": 1055485,
                "comments": 5,
                "bookmarks": 2,
                "likes": 0,
                "shares": 0,
                "typeId": 0,
                "questionText": "Cho hình vẽ dưới đây, số đo góc <img style = \"vertical-align:middle\" src= \"https://asset.moon.vn/new-latex/2025/10/de56a72e-2719-49aa-9380-29fa7eda403f.png\"/> là<br><img src=\"https://asset.moon.vn/img/chat/large/2025/10/48b1c40f-074a-4d42-b8d3-f37a147b7a82.jpg\" data-filename=\"\" style=\"max-width: 600px; height: auto;\">",
                "answer": "<b>🔍 Phương pháp</b><br>Để tìm số đo góc M, ta thực hiện hai bước:<br>1. <b>Tìm số đo góc trong tại đỉnh P:</b> Góc trong tại P và góc ngoài <img style = \"vertical-align:middle\" src= \"https://asset.moon.vn/new-latex/2025/10/8b94e2f6-562d-4834-8564-c7b2ab32f601.png\"/> là hai góc kề bù, có tổng bằng <img style = \"vertical-align:middle\" src= \"https://asset.moon.vn/new-latex/2025/10/29882ace-9824-4a2b-89a7-801ec216d6aa.png\"/>.<br>2. <b>Tìm số đo góc M:</b> Sử dụng định lý tổng bốn góc của một tứ giác (luôn bằng <img style = \"vertical-align:middle\" src= \"https://asset.moon.vn/new-latex/2025/10/67b4d92b-9149-4f62-bdd8-351a1fbe1106.png\"/>) để tìm góc còn lại.<br><b>✍️ Lời giải chi tiết</b><br><b>Bước 1: Tìm số đo góc <img style = \"vertical-align:middle\" src= \"https://asset.moon.vn/new-latex/2025/10/4bb8efda-ef18-49a8-9d37-919150ec2f20.png\"/></b><br>Góc <img style = \"vertical-align:middle\" src= \"https://asset.moon.vn/new-latex/2025/10/a63c2623-21a4-4e2d-9923-99d6a7888575.png\"/> (góc trong tại đỉnh P) và góc ngoài <img style = \"vertical-align:middle\" src= \"https://asset.moon.vn/new-latex/2025/10/0a7dc938-180c-4c32-93e9-73190f0f46f5.png\"/> là hai góc kề bù, do đó:<br><img style = \"vertical-align:middle\" src= \"https://asset.moon.vn/new-latex/2025/10/e1eaf298-d4fd-45af-883d-b9a8a7005f33.png\"/><br><img style = \"vertical-align:middle\" src= \"https://asset.moon.vn/new-latex/2025/10/8d2f026e-1e31-4f31-b01d-1a07c7e2aa85.png\"/><br><img style = \"vertical-align:middle\" src= \"https://asset.moon.vn/new-latex/2025/10/fa9a98a4-974a-40bd-9c50-ea802db51bd6.png\"/><br><b>Bước 2: Tìm số đo góc <img style = \"vertical-align:middle\" src= \"https://asset.moon.vn/new-latex/2025/10/388dec93-4fba-409f-a916-150568df2c7c.png\"/></b><br>Theo định lý tổng các góc của một tứ giác: <img style = \"vertical-align:middle\" src= \"https://asset.moon.vn/new-latex/2025/10/b106acf2-3d3e-4960-a6d4-00797b817b63.png\"/><br>Thay các giá trị đã biết vào biểu thức:<br><img style = \"vertical-align:middle\" src= \"https://asset.moon.vn/new-latex/2025/10/9ff39658-7e92-4573-b2f3-9e9a5258b2bc.png\"/><br><img style = \"vertical-align:middle\" src= \"https://asset.moon.vn/new-latex/2025/10/f5a845d5-4f23-4d52-ac0e-c441694b78fd.png\"/><br><img style = \"vertical-align:middle\" src= \"https://asset.moon.vn/new-latex/2025/10/74d8ef8e-7b15-4a8d-9df8-dfb67db68150.png\"/><br><img style = \"vertical-align:middle\" src= \"https://asset.moon.vn/new-latex/2025/10/55a3fe39-20a9-4096-9321-22b4367041a1.png\"/><br><img style = \"vertical-align:middle\" src= \"https://asset.moon.vn/new-latex/2025/10/8a7d4efc-2485-41d3-b245-9fd67d075f79.png\"/><br><b>✅ Kết luận: Chọn đáp án D</b><br>",
                "key": "D",
                "isVideo": true,
                "score": 0,
                "order": 16,
                "fillKey": "",
                "yourKey": "",
                "isTested": false,
                "isBookmark": false,
                "liked": false,
                "questionScore": 0.5,
                "plans": [],
                "answerPlans": []
            },
            {
                "questionId": 21185633,
                "lessonId": 0,
                "a": "<img style = \"vertical-align:middle\" src= \"https://asset.moon.vn/new-latex/2025/10/9567a5f9-1248-49fc-a556-14ad62af891d.png\"/>",
                "b": "<img style = \"vertical-align:middle\" src= \"https://asset.moon.vn/new-latex/2025/10/98b758fe-0ee1-4359-acdd-d8414fc1b25a.png\"/>",
                "c": "<img style = \"vertical-align:middle\" src= \"https://asset.moon.vn/new-latex/2025/10/d5426b51-a814-4a11-960b-85bccd327ad3.png\"/>",
                "d": "<img style = \"vertical-align:middle\" src= \"https://asset.moon.vn/new-latex/2025/10/77a6d07a-c188-4a3f-9937-7d70f9436daa.png\"/>",
                "bookId": 1055486,
                "comments": 1,
                "bookmarks": 6,
                "likes": 0,
                "shares": 0,
                "typeId": 0,
                "questionText": "Cho tứ giác <img style = \"vertical-align:middle\" src= \"https://asset.moon.vn/new-latex/2025/10/16d95126-e36a-438d-85b1-8957ff106860.png\"/> có <img style = \"vertical-align:middle\" src= \"https://asset.moon.vn/new-latex/2025/10/1d3cbd5a-2ecf-4e73-8a33-153925c590a7.png\"/> Số đo các góc của tứ giác này là",
                "answer": "<b>🔍 Phương pháp</b><br>Để tìm số đo các góc của tứ giác, ta sử dụng hai kiến thức:<br>1. Tổng số đo bốn góc của một tứ giác luôn bằng <img style = \"vertical-align:middle\" src= \"https://asset.moon.vn/new-latex/2025/10/b2fbb838-cdf1-4bba-902a-2f25b0c393c7.png\"/>.<br>2. Áp dụng tính chất của dãy tỉ số bằng nhau.<br><b>✍️ Lời giải chi tiết</b><br>Theo định lý tổng các góc của một tứ giác: <img style = \"vertical-align:middle\" src= \"https://asset.moon.vn/new-latex/2025/10/b6467941-8bbb-48af-98f0-e8311f83b028.png\"/><br>Theo đề bài, tỉ lệ các góc là:<br><img style = \"vertical-align:middle\" src= \"https://asset.moon.vn/new-latex/2025/10/8bb79671-2c5d-4863-9569-3df1d1d2a444.png\"/><br>Hay: <img style = \"vertical-align:middle\" src= \"https://asset.moon.vn/new-latex/2025/10/05cc9756-1972-4429-b73d-33a44c3d4ce9.png\"/><br>Áp dụng tính chất dãy tỉ số bằng nhau:<br><img style = \"vertical-align:middle\" src= \"https://asset.moon.vn/new-latex/2025/10/615dc8e3-c7cc-4755-96bf-597eeb69b0cf.png\"/><br>Từ đó, tính số đo từng góc:<br>- <img style = \"vertical-align:middle\" src= \"https://asset.moon.vn/new-latex/2025/10/27a15451-c149-4485-9cb6-8f2b40580bd5.png\"/><br>- <img style = \"vertical-align:middle\" src= \"https://asset.moon.vn/new-latex/2025/10/f1a36cb9-c907-4846-9576-212d19fe467a.png\"/><br>- <img style = \"vertical-align:middle\" src= \"https://asset.moon.vn/new-latex/2025/10/cc734496-aa84-4a90-828f-d8a0b3330745.png\"/><br>- <img style = \"vertical-align:middle\" src= \"https://asset.moon.vn/new-latex/2025/10/5bf0f4a8-d12d-4859-9550-ce212d369188.png\"/><br>Vậy, số đo các góc của tứ giác lần lượt là <img style = \"vertical-align:middle\" src= \"https://asset.moon.vn/new-latex/2025/10/16478ee2-d7da-400a-8d95-d9f6317e29c0.png\"/>.<br><b>✅ Kết luận: Chọn đáp án A</b><br>",
                "key": "A",
                "isVideo": true,
                "score": 0,
                "order": 17,
                "fillKey": "",
                "yourKey": "",
                "isTested": false,
                "isBookmark": false,
                "liked": false,
                "questionScore": 0.5,
                "plans": [],
                "answerPlans": []
            },
            {
                "questionId": 21185637,
                "lessonId": 0,
                "a": "<img style = \"vertical-align:middle\" src= \"https://asset.moon.vn/new-latex/2025/10/2e46cf88-84e5-4fb2-bacf-73d40cb88476.png\"/>",
                "b": "<img style = \"vertical-align:middle\" src= \"https://asset.moon.vn/new-latex/2025/10/2db850a6-052b-4659-96c0-d98e3e2f19fc.png\"/>",
                "c": "<img style = \"vertical-align:middle\" src= \"https://asset.moon.vn/new-latex/2025/10/29dd0682-1ba2-4620-8319-973b318f8101.png\"/>",
                "d": "<img style = \"vertical-align:middle\" src= \"https://asset.moon.vn/new-latex/2025/10/0d1a711c-c092-4134-be0e-fe150eb47bf5.png\"/>",
                "bookId": 1055487,
                "comments": 1,
                "bookmarks": 13,
                "likes": 0,
                "shares": 0,
                "typeId": 0,
                "questionText": "Cho tứ giác <img style = \"vertical-align:middle\" src= \"https://asset.moon.vn/new-latex/2025/10/1edfbe75-aaaa-4a23-b1a5-58cfa99b1c84.png\"/> có <img style = \"vertical-align:middle\" src= \"https://asset.moon.vn/new-latex/2025/10/88e84999-130c-432c-ac29-e4eefe69a8d1.png\"/> Số đo góc <img style = \"vertical-align:middle\" src= \"https://asset.moon.vn/new-latex/2025/10/8b08d7a2-261e-4a19-a249-e641018f93b6.png\"/> và góc <img style = \"vertical-align:middle\" src= \"https://asset.moon.vn/new-latex/2025/10/00abba62-560c-43e9-aace-3581e76381d1.png\"/> là",
                "answer": "<b>🔍 Phương pháp</b><br>Để tìm số đo của góc C và góc D, ta sẽ giải một hệ phương trình:<br>1. <b>Phương trình 1:</b> Dùng định lý tổng bốn góc của một tứ giác (luôn bằng <img style = \"vertical-align:middle\" src= \"https://asset.moon.vn/new-latex/2025/10/746ad910-0a30-42b0-bfb9-d9779a54d76e.png\"/>) để tìm tổng <img style = \"vertical-align:middle\" src= \"https://asset.moon.vn/new-latex/2025/10/fefe136a-8486-43b3-8b22-f668dabf94a1.png\"/>.<br>2. <b>Phương trình 2:</b> Sử dụng giả thiết của đề bài là <img style = \"vertical-align:middle\" src= \"https://asset.moon.vn/new-latex/2025/10/169c33ae-7588-489d-97ae-a343c354bde2.png\"/>.<br>3. <b>Giải hệ hai phương trình</b> trên để tìm ra giá trị cụ thể của <img style = \"vertical-align:middle\" src= \"https://asset.moon.vn/new-latex/2025/10/0d5b2305-01fd-438e-a9d0-d8948bb09b06.png\"/> và <img style = \"vertical-align:middle\" src= \"https://asset.moon.vn/new-latex/2025/10/473fc25a-2440-4da0-9369-deaafe75cc39.png\"/>.<br><b>✍️ Lời giải chi tiết</b><br><b>Bước 1: Tìm tổng <img style = \"vertical-align:middle\" src= \"https://asset.moon.vn/new-latex/2025/10/d53b9193-104d-409c-95b6-109cfdde571b.png\"/></b><br>Theo định lý tổng các góc của một tứ giác:<br><img style = \"vertical-align:middle\" src= \"https://asset.moon.vn/new-latex/2025/10/be711baf-be06-406f-94b3-045d464d1b04.png\"/><br>Thay số đo các góc đã biết vào:<br><img style = \"vertical-align:middle\" src= \"https://asset.moon.vn/new-latex/2025/10/d67ff719-0bfd-443a-9eb3-b2f586df253a.png\"/><br><img style = \"vertical-align:middle\" src= \"https://asset.moon.vn/new-latex/2025/10/9bd819fa-ffd4-4aa8-b560-e4b05574440d.png\"/><br>Suy ra tổng của <img style = \"vertical-align:middle\" src= \"https://asset.moon.vn/new-latex/2025/10/dc8cd0d4-73ea-449f-b477-b79515b83749.png\"/> và <img style = \"vertical-align:middle\" src= \"https://asset.moon.vn/new-latex/2025/10/d3306981-7ce2-45ba-9abd-9465c8aff0c7.png\"/>:<br><img style = \"vertical-align:middle\" src= \"https://asset.moon.vn/new-latex/2025/10/5b7512c2-1779-41cc-8dbb-d18f88f90ff3.png\"/><br><b>Bước 2: Giải hệ phương trình</b><br>Theo đề bài: <img style = \"vertical-align:middle\" src= \"https://asset.moon.vn/new-latex/2025/10/1eda92ac-acb4-4bb2-9ca2-90f9a6414e26.png\"/><br>Cộng vế theo vế phương trình (1) và (2) để tìm <img style = \"vertical-align:middle\" src= \"https://asset.moon.vn/new-latex/2025/10/f597050d-8a51-4b8b-a4f1-7a15bfcc3e70.png\"/>:<br><img style = \"vertical-align:middle\" src= \"https://asset.moon.vn/new-latex/2025/10/7c37af18-eb29-460a-a505-862dbe9d2e8e.png\"/><br><img style = \"vertical-align:middle\" src= \"https://asset.moon.vn/new-latex/2025/10/4055a5ac-0834-4393-8df0-a66e58337a9b.png\"/><br><img style = \"vertical-align:middle\" src= \"https://asset.moon.vn/new-latex/2025/10/d120de28-74aa-4991-8de4-ed0630b7bbdb.png\"/><br>Thay giá trị của <img style = \"vertical-align:middle\" src= \"https://asset.moon.vn/new-latex/2025/10/f671d158-de09-4610-9c6b-749420e61e85.png\"/> vào phương trình (1) để tìm <img style = \"vertical-align:middle\" src= \"https://asset.moon.vn/new-latex/2025/10/907872fd-e3cb-4cf7-8023-94af32e4a469.png\"/>:<br><img style = \"vertical-align:middle\" src= \"https://asset.moon.vn/new-latex/2025/10/606241f2-9bbb-4e76-9522-d9b828478883.png\"/><br><img style = \"vertical-align:middle\" src= \"https://asset.moon.vn/new-latex/2025/10/2e2503e8-ec61-473e-a88b-16bedccbdd2c.png\"/><br>Vậy, số đo góc C là <img style = \"vertical-align:middle\" src= \"https://asset.moon.vn/new-latex/2025/10/541d6b92-65af-4731-bc84-ed45a6afe07a.png\"/> và góc D là <img style = \"vertical-align:middle\" src= \"https://asset.moon.vn/new-latex/2025/10/10f12b18-a938-43de-bab2-d697be5ed064.png\"/>.<br><b>✅ Kết luận: Chọn đáp án B</b><br>",
                "key": "B",
                "isVideo": true,
                "score": 0,
                "order": 18,
                "fillKey": "",
                "yourKey": "",
                "isTested": false,
                "isBookmark": false,
                "liked": false,
                "questionScore": 0.5,
                "plans": [],
                "answerPlans": []
            },
            {
                "questionId": 21185641,
                "lessonId": 0,
                "a": "<img style = \"vertical-align:middle\" src= \"https://asset.moon.vn/new-latex/2025/10/33d53d7c-131a-4988-a99e-d96e87518cce.png\"/>",
                "b": "<img style = \"vertical-align:middle\" src= \"https://asset.moon.vn/new-latex/2025/10/6c869c31-09bf-469b-9d24-ade761e5db18.png\"/>",
                "c": "<img style = \"vertical-align:middle\" src= \"https://asset.moon.vn/new-latex/2025/10/3bb8900c-f5b1-48ea-814a-8daaeb9f499f.png\"/>",
                "d": "<img style = \"vertical-align:middle\" src= \"https://asset.moon.vn/new-latex/2025/10/89789b1e-67fe-455b-8001-8f51b276e89e.png\"/>",
                "bookId": 1055488,
                "comments": 6,
                "bookmarks": 1,
                "likes": 0,
                "shares": 0,
                "typeId": 0,
                "questionText": "Cho tứ giác <img style = \"vertical-align:middle\" src= \"https://asset.moon.vn/new-latex/2025/10/64f4f458-e004-4dae-bc53-8697b08a4f8b.png\"/> có <img style = \"vertical-align:middle\" src= \"https://asset.moon.vn/new-latex/2025/10/2e6f1a0d-2d39-4f9a-a01e-ee72751da970.png\"/> Số đo góc ngoài tại đỉnh <img style = \"vertical-align:middle\" src= \"https://asset.moon.vn/new-latex/2025/10/14b259c1-44c5-4040-975d-5efbbdd23122.png\"/> là",
                "answer": "<b><font color=\"#f44336\">Đính chính: Nhóm tác giả xin gửi lời xin lỗi chân thành đến các em học sinh. Trong quá trình biên soạn tài liệu, không tránh khỏi có sơ sót. Các em sửa lại đề bài như trên web. Sai sót này sẽ được sửa trong lần tái bản sau. Cảm ơn các em! <br></font></b><b>🔍 Phương pháp</b><br>Để giải bài toán, ta sẽ thực hiện hai bước:<br>1. <b>Tìm số đo góc trong <img style = \"vertical-align:middle\" src= \"https://asset.moon.vn/new-latex/2025/10/b3b9655f-31de-433c-9a68-d99be6ee9a66.png\"/>:</b> Sử dụng định lý tổng bốn góc của một tứ giác (luôn bằng <img style = \"vertical-align:middle\" src= \"https://asset.moon.vn/new-latex/2025/10/43938861-b6b4-4b43-ad39-21c309de1934.png\"/>) để tìm số đo của góc <img style = \"vertical-align:middle\" src= \"https://asset.moon.vn/new-latex/2025/10/231e8f4f-ed32-4c32-8616-51796bc281d1.png\"/>.<br>2. <b>Tìm số đo góc ngoài tại đỉnh D:</b> Sử dụng tính chất của góc trong và góc ngoài kề nhau tại một đỉnh (luôn có tổng bằng <img style = \"vertical-align:middle\" src= \"https://asset.moon.vn/new-latex/2025/10/f1fe38c0-3ac4-416d-adc8-f3a139af97f7.png\"/>) để tìm ra đáp án.<br><b>✍️ Lời giải chi tiết</b><br><b>Bước 1: Tìm số đo góc trong <img style = \"vertical-align:middle\" src= \"https://asset.moon.vn/new-latex/2025/10/e57c1ba1-b147-473d-be9d-afee84f2c36f.png\"/></b><br>Tổng các góc trong của tứ giác ABCD là <img style = \"vertical-align:middle\" src= \"https://asset.moon.vn/new-latex/2025/10/7600c6b2-a019-4a89-a137-b0146681f770.png\"/>:<br><img style = \"vertical-align:middle\" src= \"https://asset.moon.vn/new-latex/2025/10/479f3b36-24b5-4dc1-9953-7ea4d0707a1a.png\"/><br>Thay các giá trị đã cho vào:<br><img style = \"vertical-align:middle\" src= \"https://asset.moon.vn/new-latex/2025/10/5c94883b-b31b-44ab-8f1f-0613bbe4b346.png\"/><br><img style = \"vertical-align:middle\" src= \"https://asset.moon.vn/new-latex/2025/10/f69fef9b-80bf-4d40-be55-9f7a4eaf1409.png\"/><br><img style = \"vertical-align:middle\" src= \"https://asset.moon.vn/new-latex/2025/10/f10a39e4-0d78-471d-bd59-d012f56474ed.png\"/><br><img style = \"vertical-align:middle\" src= \"https://asset.moon.vn/new-latex/2025/10/a41d200a-5c55-40bf-b054-a39745b9171e.png\"/><br><b>Bước 2: Tìm số đo góc ngoài tại đỉnh D</b><br>Góc trong và góc ngoài tại cùng một đỉnh là hai góc kề bù, có tổng bằng <img style = \"vertical-align:middle\" src= \"https://asset.moon.vn/new-latex/2025/10/4ebf6b7a-4364-4409-940b-5482d66e7193.png\"/>. Gọi góc ngoài tại đỉnh D là <img style = \"vertical-align:middle\" src= \"https://asset.moon.vn/new-latex/2025/10/1dd19ab9-1bbf-4359-97e2-5e3656b39d85.png\"/>:<br><img style = \"vertical-align:middle\" src= \"https://asset.moon.vn/new-latex/2025/10/1ced48ab-d143-49c5-b808-317bcfbf4107.png\"/><br><img style = \"vertical-align:middle\" src= \"https://asset.moon.vn/new-latex/2025/10/77b89f03-154e-49f7-b772-a6656c2fb4d3.png\"/><br><img style = \"vertical-align:middle\" src= \"https://asset.moon.vn/new-latex/2025/10/8a5ce9eb-142b-4d1f-8e78-e1b655d58661.png\"/><br><b>✅ Kết luận: Chọn đáp án D</b>",
                "key": "D",
                "isVideo": true,
                "score": 0,
                "order": 19,
                "fillKey": "",
                "yourKey": "",
                "isTested": false,
                "isBookmark": false,
                "liked": false,
                "questionScore": 0.5,
                "plans": [],
                "answerPlans": []
            },
            {
                "questionId": 21185645,
                "lessonId": 0,
                "a": "<img style = \"vertical-align:middle\" src= \"https://asset.moon.vn/new-latex/2025/10/463df300-44f1-405e-9055-934849ecfcde.png\"/>",
                "b": "<img style = \"vertical-align:middle\" src= \"https://asset.moon.vn/new-latex/2025/10/1cb9d7e1-1dda-46e3-bf36-eb4266c57d95.png\"/>",
                "c": "<img style = \"vertical-align:middle\" src= \"https://asset.moon.vn/new-latex/2025/10/b5545b18-6271-4e4f-b20d-5e56136efd08.png\"/>",
                "d": "<img style = \"vertical-align:middle\" src= \"https://asset.moon.vn/new-latex/2025/10/78f5d94f-ff44-43f9-9a1a-56ee3f0b0282.png\"/>",
                "bookId": 1055489,
                "comments": 9,
                "bookmarks": 10,
                "likes": 0,
                "shares": 0,
                "typeId": 0,
                "questionText": "Cho tứ giác ABCD có <img style = \"vertical-align:middle\" src= \"https://asset.moon.vn/new-latex/2025/10/c15c69a2-b144-463d-9bee-ef9f07578618.png\"/> Số đo góc A là",
                "answer": "<img src=\"https://asset.moon.vn/img/chat/large/2025/10/e225117c-e405-4fec-8c5b-a6402c86da3b.jpg\" data-filename=\"\" style=\"max-width: 600px; height: auto;\"> <br><b>🔍 Phương pháp</b><br>1. <b>Phân tích hình dạng:</b> Tứ giác ABCD có hai cặp cạnh kề bằng nhau là <img style = \"vertical-align:middle\" src= \"https://asset.moon.vn/new-latex/2025/10/af714671-8bc8-4d76-954f-6a3409e5f388.png\"/> và <img style = \"vertical-align:middle\" src= \"https://asset.moon.vn/new-latex/2025/10/d23b5e9d-c141-4704-b574-5cad0d77eab0.png\"/>, đây là dạng hình \"cái diều\" (kite).<br>2. <b>Chứng minh góc bằng nhau:</b> Chứng minh <img style = \"vertical-align:middle\" src= \"https://asset.moon.vn/new-latex/2025/10/c2021ddc-e607-4b31-a27d-66450f4f68c3.png\"/> bằng trường hợp cạnh-cạnh-cạnh (c.c.c). Từ đó, suy ra <img style = \"vertical-align:middle\" src= \"https://asset.moon.vn/new-latex/2025/10/31a451e4-cdef-4f8d-b3bc-1f256c83c531.png\"/>.<br>3. <b>Tính góc:</b> Áp dụng định lý tổng bốn góc của tứ giác để tìm <img style = \"vertical-align:middle\" src= \"https://asset.moon.vn/new-latex/2025/10/bc17738b-f79b-46b4-a26c-f48ca3a1bdb1.png\"/>.<br><b>✍️ Lời giải chi tiết</b><br>Vẽ đường chéo <img style = \"vertical-align:middle\" src= \"https://asset.moon.vn/new-latex/2025/10/c0d3a731-e182-4130-88e8-d30da513cd87.png\"/> chia tứ giác thành hai tam giác <img style = \"vertical-align:middle\" src= \"https://asset.moon.vn/new-latex/2025/10/e49e1e34-69a2-428c-824b-9cddf71f2381.png\"/> và <img style = \"vertical-align:middle\" src= \"https://asset.moon.vn/new-latex/2025/10/fb09ef5b-2a84-43b6-a8bc-cf0afbf3dfa9.png\"/>.<br>Xét <img style = \"vertical-align:middle\" src= \"https://asset.moon.vn/new-latex/2025/10/642914e1-445f-403e-892c-4e949e2fce08.png\"/> và <img style = \"vertical-align:middle\" src= \"https://asset.moon.vn/new-latex/2025/10/accd169f-8fc7-44e5-8014-0ef16cb45d5b.png\"/>:<br>- <img style = \"vertical-align:middle\" src= \"https://asset.moon.vn/new-latex/2025/10/d986e97c-cad3-4083-8b79-01d37c8d9b01.png\"/><br>- <img style = \"vertical-align:middle\" src= \"https://asset.moon.vn/new-latex/2025/10/a5fd5da8-b2e4-4de4-9ee4-4f2ee437e45d.png\"/><br>- <img style = \"vertical-align:middle\" src= \"https://asset.moon.vn/new-latex/2025/10/e0e8d6b8-e92a-4d29-b587-fdfe1355ce44.png\"/> là cạnh chung<br>=> <img style = \"vertical-align:middle\" src= \"https://asset.moon.vn/new-latex/2025/10/4028b86c-f90c-4e45-be92-a37307e3b309.png\"/> (c.c.c)<br>=> <img style = \"vertical-align:middle\" src= \"https://asset.moon.vn/new-latex/2025/10/e77a4928-1dc7-427b-bad1-b62efd24967f.png\"/> hay <img style = \"vertical-align:middle\" src= \"https://asset.moon.vn/new-latex/2025/10/5ff33584-d379-430a-ac23-e05ad843ec7c.png\"/>.<br>Áp dụng tổng các góc tứ giác:<br><img style = \"vertical-align:middle\" src= \"https://asset.moon.vn/new-latex/2025/10/4e0df83c-abcc-46da-ac8e-f6d74a7ae59a.png\"/><br>Thay <img style = \"vertical-align:middle\" src= \"https://asset.moon.vn/new-latex/2025/10/a9f5db9d-d588-4dc0-ba00-85f2f22c85b3.png\"/> và các giá trị đã biết:<br><img style = \"vertical-align:middle\" src= \"https://asset.moon.vn/new-latex/2025/10/d62a897f-faca-46ea-8a1f-c2aa3cd6fc9b.png\"/><br><img style = \"vertical-align:middle\" src= \"https://asset.moon.vn/new-latex/2025/10/a1c5ad99-b8cc-46be-b825-36698b15165b.png\"/><br><img style = \"vertical-align:middle\" src= \"https://asset.moon.vn/new-latex/2025/10/c6082beb-3321-41cd-9935-b8f1adf20ffc.png\"/><br><img style = \"vertical-align:middle\" src= \"https://asset.moon.vn/new-latex/2025/10/9a4579f3-d1de-42c3-a9eb-b96fa1c6155a.png\"/><br>Vậy <img style = \"vertical-align:middle\" src= \"https://asset.moon.vn/new-latex/2025/10/fc346690-9fdd-44cc-a521-a0a81c25edf4.png\"/> và <img style = \"vertical-align:middle\" src= \"https://asset.moon.vn/new-latex/2025/10/bd9c5aec-fed8-49f5-b6fa-d36d59139653.png\"/>.<br><b>✅ Kết luận: Chọn đáp án B</b>",
                "key": "B",
                "isVideo": true,
                "score": 0,
                "order": 20,
                "fillKey": "",
                "yourKey": "",
                "isTested": false,
                "isBookmark": false,
                "liked": false,
                "questionScore": 0.5,
                "plans": [],
                "answerPlans": []
            }
        ]
    }
]